odoo/addons/sale_stock_line_customer_ref/README.rst
odoo/addons/sale_stock_line_customer_ref/__init__.py
odoo/addons/sale_stock_line_customer_ref/__manifest__.py
odoo/addons/sale_stock_line_customer_ref/hooks.py
odoo/addons/sale_stock_line_customer_ref/i18n/es.po
odoo/addons/sale_stock_line_customer_ref/i18n/it.po
odoo/addons/sale_stock_line_customer_ref/i18n/nl.po
odoo/addons/sale_stock_line_customer_ref/i18n/pt.po
odoo/addons/sale_stock_line_customer_ref/i18n/sale_stock_line_customer_ref.pot
odoo/addons/sale_stock_line_customer_ref/models/__init__.py
odoo/addons/sale_stock_line_customer_ref/models/sale_order_line.py
odoo/addons/sale_stock_line_customer_ref/models/stock_move.py
odoo/addons/sale_stock_line_customer_ref/models/stock_move_line.py
odoo/addons/sale_stock_line_customer_ref/models/stock_package_level.py
odoo/addons/sale_stock_line_customer_ref/models/stock_picking.py
odoo/addons/sale_stock_line_customer_ref/models/stock_quant_package.py
odoo/addons/sale_stock_line_customer_ref/readme/CONTRIBUTORS.md
odoo/addons/sale_stock_line_customer_ref/readme/CREDITS.md
odoo/addons/sale_stock_line_customer_ref/readme/DESCRIPTION.md
odoo/addons/sale_stock_line_customer_ref/readme/USAGE.md
odoo/addons/sale_stock_line_customer_ref/static/description/icon.png
odoo/addons/sale_stock_line_customer_ref/static/description/index.html
odoo/addons/sale_stock_line_customer_ref/tests/__init__.py
odoo/addons/sale_stock_line_customer_ref/tests/test_customer_ref.py
odoo/addons/sale_stock_line_customer_ref/views/sale_order.xml
odoo/addons/sale_stock_line_customer_ref/views/stock_move.xml
odoo/addons/sale_stock_line_customer_ref/views/stock_move_line.xml
odoo/addons/sale_stock_line_customer_ref/views/stock_package_level.xml
odoo/addons/sale_stock_line_customer_ref/views/stock_picking.xml
odoo/addons/sale_stock_line_customer_ref/views/stock_quant_package.xml
odoo_addon_sale_stock_line_customer_ref-18.0.1.0.0.8.dist-info/METADATA
odoo_addon_sale_stock_line_customer_ref-18.0.1.0.0.8.dist-info/WHEEL
odoo_addon_sale_stock_line_customer_ref-18.0.1.0.0.8.dist-info/top_level.txt
odoo_addon_sale_stock_line_customer_ref-18.0.1.0.0.8.dist-info/RECORD
