Metadata-Version: 2.1
Name: odoo-addon-sale_stock_line_customer_ref
Version: 18.0.1.0.0.8
Requires-Python: >=3.10
Requires-Dist: odoo==18.0.*
Summary: Allow you to add a customer reference on order lines propagaged to move operations.
Home-page: https://github.com/OCA/sale-workflow
License: AGPL-3
Author: Camptocamp, Odoo Community Association (OCA)
Author-email: support@odoo-community.org
Classifier: Programming Language :: Python
Classifier: Framework :: Odoo
Classifier: Framework :: Odoo :: 18.0
Classifier: License :: OSI Approved :: GNU Affero General Public License v3
Classifier: Development Status :: 4 - Beta
